{
  "tickers": {
    "ABT": {
      "added": "2026-04-16T12:16:40Z",
      "tier": 1
    },
    "AEHR": {
      "added": "2026-04-16T12:16:40Z",
      "tier": 1
    },
    "ALM": {
      "added": "2026-04-16T12:16:40Z",
      "tier": 1
    },
    "ANL": {
      "added": "2026-04-16T12:16:40Z",
      "tier": 1
    },
    "ANNA": {
      "added": "2026-04-16T12:16:40Z",
      "tier": 1
    },
    "ARQQ": {
      "added": "2026-04-16T12:16:40Z",
      "tier": 1
    },
    "ASMG": {
      "added": "2026-04-16T12:16:40Z",
      "tier": 1
    },
    "AVBP": {
      "added": "2026-04-16T12:16:40Z",
      "tier": 1
    },
    "AVXL": {
      "added": "2026-04-16T12:16:40Z",
      "tier": 1
    },
    "BIRD": {
      "added": "2026-04-16T12:16:40Z",
      "tier": 1
    },
    "BNAI": {
      "added": "2026-04-16T12:16:40Z",
      "tier": 1
    },
    "BTQ": {
      "added": "2026-04-16T12:16:40Z",
      "tier": 1
    },
    "CAR": {
      "added": "2026-04-16T12:16:40Z",
      "tier": 1
    },
    "CDNA": {
      "added": "2026-04-16T12:16:40Z",
      "tier": 1
    },
    "CTXR": {
      "added": "2026-04-16T12:16:40Z",
      "tier": 1
    },
    "ELAB": {
      "added": "2026-04-16T12:16:40Z",
      "tier": 1
    },
    "EOSE": {
      "added": "2026-04-16T12:16:40Z",
      "tier": 1
    },
    "ETHT": {
      "added": "2026-04-16T12:16:40Z",
      "tier": 1
    },
    "EVTL": {
      "added": "2026-04-16T12:16:40Z",
      "tier": 1
    },
    "FBGL": {
      "added": "2026-04-16T12:16:40Z",
      "tier": 1
    },
    "FC": {
      "added": "2026-04-16T12:16:40Z",
      "tier": 1
    },
    "FIG": {
      "added": "2026-04-16T12:16:40Z",
      "tier": 1
    },
    "GLWG": {
      "added": "2026-04-16T12:16:40Z",
      "tier": 1
    },
    "GVH": {
      "added": "2026-04-16T12:16:40Z",
      "tier": 1
    },
    "HIMS": {
      "added": "2026-04-16T12:16:40Z",
      "tier": 1
    },
    "HIMZ": {
      "added": "2026-04-16T12:16:40Z",
      "tier": 1
    },
    "HIVE": {
      "added": "2026-04-16T12:16:40Z",
      "tier": 1
    },
    "HQ": {
      "added": "2026-04-16T12:16:40Z",
      "tier": 1
    },
    "HROW": {
      "added": "2026-04-16T12:16:40Z",
      "tier": 1
    },
    "HYPD": {
      "added": "2026-04-16T12:16:40Z",
      "tier": 1
    },
    "IMRX": {
      "added": "2026-04-16T12:16:40Z",
      "tier": 1
    },
    "IONL": {
      "added": "2026-04-16T12:16:40Z",
      "tier": 1
    },
    "IONQ": {
      "added": "2026-04-16T12:16:40Z",
      "tier": 1
    },
    "IONX": {
      "added": "2026-04-16T12:16:40Z",
      "tier": 1
    },
    "IONZ": {
      "added": "2026-04-16T12:16:40Z",
      "tier": 1
    },
    "JKS": {
      "added": "2026-04-16T12:16:40Z",
      "tier": 1
    },
    "KLRS": {
      "added": "2026-04-16T12:16:40Z",
      "tier": 1
    },
    "KPTI": {
      "added": "2026-04-16T12:16:40Z",
      "tier": 1
    },
    "LASE": {
      "added": "2026-04-16T12:16:40Z",
      "tier": 1
    },
    "LEU": {
      "added": "2026-04-16T12:16:40Z",
      "tier": 1
    },
    "LTRN": {
      "added": "2026-04-16T12:16:40Z",
      "tier": 1
    },
    "LVWR": {
      "added": "2026-04-16T12:16:40Z",
      "tier": 1
    },
    "MNPR": {
      "added": "2026-04-16T12:16:40Z",
      "tier": 1
    },
    "MRLN": {
      "added": "2026-04-16T12:16:40Z",
      "tier": 1
    },
    "MULL": {
      "added": "2026-04-16T12:16:40Z",
      "tier": 1
    },
    "MUU": {
      "added": "2026-04-16T12:16:40Z",
      "tier": 1
    },
    "MYSE": {
      "added": "2026-04-16T12:16:40Z",
      "tier": 1
    },
    "NCI": {
      "added": "2026-04-16T12:16:40Z",
      "tier": 1
    },
    "NEXA": {
      "added": "2026-04-16T12:16:40Z",
      "tier": 1
    },
    "NICM": {
      "added": "2026-04-16T12:16:40Z",
      "tier": 1
    },
    "NN": {
      "added": "2026-04-16T12:16:40Z",
      "tier": 1
    },
    "NNE": {
      "added": "2026-04-16T12:16:40Z",
      "tier": 1
    },
    "NUAI": {
      "added": "2026-04-16T12:16:40Z",
      "tier": 1
    },
    "OKLL": {
      "added": "2026-04-16T12:16:40Z",
      "tier": 1
    },
    "OKLO": {
      "added": "2026-04-16T12:16:40Z",
      "tier": 1
    },
    "OKLS": {
      "added": "2026-04-16T12:16:40Z",
      "tier": 1
    },
    "ONCO": {
      "added": "2026-04-16T12:16:40Z",
      "tier": 1
    },
    "ORC": {
      "added": "2026-04-16T12:16:40Z",
      "tier": 1
    },
    "PENG": {
      "added": "2026-04-16T12:16:40Z",
      "tier": 1
    },
    "PGY": {
      "added": "2026-04-16T12:16:40Z",
      "tier": 1
    },
    "PLTZ": {
      "added": "2026-04-16T12:16:40Z",
      "tier": 1
    },
    "POLA": {
      "added": "2026-04-16T12:16:40Z",
      "tier": 1
    },
    "QBTZ": {
      "added": "2026-04-16T12:16:40Z",
      "tier": 1
    },
    "QDEL": {
      "added": "2026-04-16T12:16:40Z",
      "tier": 1
    },
    "QNCX": {
      "added": "2026-04-16T12:16:40Z",
      "tier": 1
    },
    "QPUX": {
      "added": "2026-04-16T12:16:40Z",
      "tier": 1
    },
    "QS": {
      "added": "2026-04-16T12:16:40Z",
      "tier": 1
    },
    "QUBT": {
      "added": "2026-04-16T12:16:40Z",
      "tier": 1
    },
    "QVCGA": {
      "added": "2026-04-16T12:16:40Z",
      "tier": 1
    },
    "RGTX": {
      "added": "2026-04-16T12:16:40Z",
      "tier": 1
    },
    "RGTZ": {
      "added": "2026-04-16T12:16:40Z",
      "tier": 1
    },
    "RKLZ": {
      "added": "2026-04-16T12:16:40Z",
      "tier": 1
    },
    "RMSG": {
      "added": "2026-04-16T12:16:40Z",
      "tier": 1
    },
    "RR": {
      "added": "2026-04-16T12:16:40Z",
      "tier": 1
    },
    "SDEV": {
      "added": "2026-04-16T12:16:40Z",
      "tier": 1
    },
    "SKYQ": {
      "added": "2026-04-16T12:16:40Z",
      "tier": 1
    },
    "SLDP": {
      "added": "2026-04-16T12:16:40Z",
      "tier": 1
    },
    "SMR": {
      "added": "2026-04-16T12:16:40Z",
      "tier": 1
    },
    "SOFX": {
      "added": "2026-04-16T12:16:40Z",
      "tier": 1
    },
    "SOUN": {
      "added": "2026-04-16T12:16:40Z",
      "tier": 1
    },
    "SOUX": {
      "added": "2026-04-16T12:16:40Z",
      "tier": 1
    },
    "SPIR": {
      "added": "2026-04-16T12:16:40Z",
      "tier": 1
    },
    "SRFM": {
      "added": "2026-04-16T12:16:40Z",
      "tier": 1
    },
    "TPET": {
      "added": "2026-04-16T12:16:40Z",
      "tier": 1
    },
    "UCAR": {
      "added": "2026-04-16T12:16:40Z",
      "tier": 1
    },
    "UGRO": {
      "added": "2026-04-16T12:16:40Z",
      "tier": 1
    },
    "ULCC": {
      "added": "2026-04-16T12:16:40Z",
      "tier": 1
    },
    "VOYG": {
      "added": "2026-04-16T12:16:40Z",
      "tier": 1
    },
    "VSA": {
      "added": "2026-04-16T12:16:40Z",
      "tier": 1
    },
    "WNW": {
      "added": "2026-04-16T12:16:40Z",
      "tier": 1
    },
    "WSHP": {
      "added": "2026-04-16T12:16:40Z",
      "tier": 1
    },
    "XNDU": {
      "added": "2026-04-16T12:16:40Z",
      "tier": 1
    },
    "XXII": {
      "added": "2026-04-16T12:16:40Z",
      "tier": 1
    },
    "YANG": {
      "added": "2026-04-16T12:16:40Z",
      "tier": 1
    }
  },
  "updated": "2026-04-16",
  "version": 1
}